enthusiast_source_sample/__init__.py
enthusiast_source_sample/document_source.py
enthusiast_source_sample/product_source.py
enthusiast_source_sample/sample_documents.csv
enthusiast_source_sample/sample_products.csv
enthusiast_source_sample-1.2.0.dist-info/METADATA
enthusiast_source_sample-1.2.0.dist-info/WHEEL
enthusiast_source_sample-1.2.0.dist-info/licenses/LICENSE.md
enthusiast_source_sample-1.2.0.dist-info/RECORD
